simpler_model/__init__.py
simpler_model/models/__init__.py
simpler_model/models/attribute.py
simpler_model/models/attribute_modifier.py
simpler_model/models/cardinality.py
simpler_model/models/entity.py
simpler_model/models/entity_modifier.py
simpler_model/models/format.py
simpler_model/models/model_schema.py
simpler_model/models/relation.py
simpler_model/models/relation_modifier.py
simpler_model-0.2.2.dist-info/METADATA
simpler_model-0.2.2.dist-info/WHEEL
simpler_model-0.2.2.dist-info/top_level.txt
simpler_model-0.2.2.dist-info/RECORD
